odoo/addons/hr_holidays_hour/README.rst
odoo/addons/hr_holidays_hour/__init__.py
odoo/addons/hr_holidays_hour/__manifest__.py
odoo/addons/hr_holidays_hour/i18n/de.po
odoo/addons/hr_holidays_hour/i18n/fr.po
odoo/addons/hr_holidays_hour/i18n/hr_holidays_hour.pot
odoo/addons/hr_holidays_hour/models/__init__.py
odoo/addons/hr_holidays_hour/models/hr_employee.py
odoo/addons/hr_holidays_hour/models/hr_holidays.py
odoo/addons/hr_holidays_hour/models/hr_holidays_status.py
odoo/addons/hr_holidays_hour/readme/CONTRIBUTORS.rst
odoo/addons/hr_holidays_hour/readme/CREDITS.rst
odoo/addons/hr_holidays_hour/readme/DESCRIPTION.rst
odoo/addons/hr_holidays_hour/readme/USAGE.rst
odoo/addons/hr_holidays_hour/report/__init__.py
odoo/addons/hr_holidays_hour/report/hr_holidays_report.py
odoo/addons/hr_holidays_hour/report/hr_holidays_report_view.xml
odoo/addons/hr_holidays_hour/security/ir.model.access.csv
odoo/addons/hr_holidays_hour/static/description/icon.png
odoo/addons/hr_holidays_hour/static/description/index.html
odoo/addons/hr_holidays_hour/tests/__init__.py
odoo/addons/hr_holidays_hour/tests/test_leave_hours.py
odoo/addons/hr_holidays_hour/tests/test_resource.py
odoo/addons/hr_holidays_hour/views/hr_holidays.xml
odoo/addons/hr_holidays_hour/views/hr_holidays_status.xml
odoo11_addon_hr_holidays_hour-11.0.1.0.0.99.dev21.dist-info/METADATA
odoo11_addon_hr_holidays_hour-11.0.1.0.0.99.dev21.dist-info/WHEEL
odoo11_addon_hr_holidays_hour-11.0.1.0.0.99.dev21.dist-info/top_level.txt
odoo11_addon_hr_holidays_hour-11.0.1.0.0.99.dev21.dist-info/RECORD
